cerasus.py
cerasus-0.0.1.dist-info/LICENSE
cerasus-0.0.1.dist-info/METADATA
cerasus-0.0.1.dist-info/WHEEL
cerasus-0.0.1.dist-info/top_level.txt
cerasus-0.0.1.dist-info/RECORD
