Metadata-Version: 2.1
Name: cerasus
Version: 0.0.1
Summary: Simple quickstarter/dispatcher for ASGI apps based on Hypercorn with Request/Response objects from Starlette.
Home-page: https://github.com/amateur80lvl/cerasus
Author: amateur80lvl
Author-email: amateur80lvl@gmail.com
Keywords: asgi,asyncio
Classifier: Development Status :: 3 - Alpha
Classifier: Intended Audience :: Developers
Classifier: Environment :: Web Environment
Classifier: Programming Language :: Python
Classifier: Operating System :: OS Independent
Classifier: License :: OSI Approved :: GNU Lesser General Public License v3 (LGPLv3)
Classifier: Topic :: Internet :: WWW/HTTP
Classifier: Topic :: Software Development :: Libraries :: Python Modules
License-File: LICENSE
Requires-Dist: hypercorn
Requires-Dist: starlette
Requires-Dist: uvloop
